LICENSE.txt
README.md
setup.py
mutual/__init__.py
mutual.egg-info/PKG-INFO
mutual.egg-info/SOURCES.txt
mutual.egg-info/dependency_links.txt
mutual.egg-info/requires.txt
mutual.egg-info/top_level.txt
mutual/api_resources/APIKey.py
mutual/api_resources/Bot.py
mutual/api_resources/Chat.py
mutual/api_resources/Dev.py
mutual/api_resources/Judge.py
mutual/api_resources/JudgeMessage.py
mutual/api_resources/Material.py
mutual/api_resources/Memory.py
mutual/api_resources/Prompt.py
mutual/api_resources/__init__.py