Metadata-Version: 2.1
Name: mutual
Version: 0.4.1
Summary: A Python client for the Mutual API.
Home-page: https://github.com/Mutu-AI
Author: Alex Betita
Author-email: alexbetita25@gmail.com
Classifier: Programming Language :: Python :: 3
Classifier: License :: OSI Approved :: MIT License
Classifier: Operating System :: OS Independent
Requires-Python: >=3.6
License-File: LICENSE.txt
